Metadata-Version: 1.1
Name: archils-second-calc
Version: 0.0.23
Summary: simple calc
Home-page: UNKNOWN
Author: archil chachanidze
Author-email: archil.chachanidze@gmail.com
License: UNKNOWN
Keywords: python,explainable ai
Platform: UNKNOWN
Classifier: Development Status :: 3 - Alpha
Classifier: Programming Language :: Python :: 3
Classifier: Operating System :: MacOS :: MacOS X
Classifier: Operating System :: Microsoft :: Windows
